<hibernate-mapping xmlns="http://www.hibernate.org/xsd/hibernate-mapping">
    <class name="magus.model.User" table="users">
        <id name="id" type="java.lang.Integer" column="id">
            <generator class="increment"/>
        </id>
        <property name="name" type="java.lang.String" column="name"/>
        <property name="password" type="java.lang.String" column="password"/>
    </class>

   <class name="magus.model.Skills" table="skills">
       <id name="id" type="java.lang.Integer" column="id">
           <generator class="increment"></generator>
       </id>
       <property name="baseSkillPoints" type="java.lang.Integer" column="baseSkillPoints"/>
       <property name="skillPointsPerLevel" type="java.lang.Integer" column="skillPointsPerLevel"/>
       <property name="skillPoints" type="java.lang.Integer" column="skillPoints"/>
   </class>

</hibernate-mapping>